reproducible_zip/__init__.py
reproducible_zip/__main__.py
reproducible_zip/zipinfo.py
reproducible_zip-0.3.0.dist-info/METADATA
reproducible_zip-0.3.0.dist-info/WHEEL
reproducible_zip-0.3.0.dist-info/entry_points.txt
reproducible_zip-0.3.0.dist-info/RECORD
