Metadata-Version: 2.4
Name: reproducible_zip
Version: 0.3.0
Summary: Reproducible ZipFile (supports shutil.archive)
Author-email: Sean Summers <165854+seansummers@users.noreply.github.com>
Requires-Python: >=3.7
